compyter/__init__.py
compyter/compyter.py
compyter/jinja.py
Compyter-0.0.4.dist-info/METADATA
Compyter-0.0.4.dist-info/WHEEL
Compyter-0.0.4.dist-info/top_level.txt
Compyter-0.0.4.dist-info/RECORD
