Metadata-Version: 2.1
Name: Compyter
Version: 0.0.4
Summary: A component parser for html
Home-page: https://github.com/spynets/compyte
Author: Alfred Roos
Author-email: alfred@stensatter.se
License: MIT
Classifier: Programming Language :: Python :: 3
Classifier: License :: OSI Approved :: MIT License
Classifier: Operating System :: OS Independent
Requires-Python: >=3.6
Requires-Dist: bs4
Requires-Dist: black
